khooshe/__init__.py
khooshe/khooshe.py
Khooshe-0.2.dist-info/DESCRIPTION.rst
Khooshe-0.2.dist-info/METADATA
Khooshe-0.2.dist-info/metadata.json
Khooshe-0.2.dist-info/RECORD
Khooshe-0.2.dist-info/top_level.txt
Khooshe-0.2.dist-info/WHEEL
