Metadata-Version: 2.0
Name: Khooshe
Version: 0.2
Summary: Big GeoSptial Data Points Visualization Tool
Home-page: https://github.com/MBoustani/Khooshe
Author: Mazi Boustani
Author-email: maziyar_b4@yahoo.com
License: Apache V2
Download-URL: https://github.com/MBoustani/Khooshe/archive/master.zip
Keywords: big geoSptial data points visualization opensource
Platform: UNKNOWN
Classifier: Development Status :: 5 - Production/Stable
Classifier: Intended Audience :: Science/Research
Classifier: License :: OSI Approved :: Apache Software License
Classifier: Operating System :: OS Independent
Classifier: Programming Language :: Python
Classifier: Topic :: Scientific/Engineering :: GIS
Classifier: Topic :: Software Development :: Libraries :: Python Modules
Classifier: Programming Language :: Python :: 2.7
Classifier: Programming Language :: Python :: Implementation :: PyPy
